faulthandler.pth
faulthandler.pyd
faulthandler-3.2.dist-info/AUTHORS
faulthandler-3.2.dist-info/COPYING
faulthandler-3.2.dist-info/METADATA
faulthandler-3.2.dist-info/WHEEL
faulthandler-3.2.dist-info/top_level.txt
faulthandler-3.2.dist-info/RECORD
