Metadata-Version: 2.1
Name: faulthandler
Version: 3.2
Summary: Display the Python traceback on a crash
Home-page: https://faulthandler.readthedocs.io/
Author: Victor Stinner
Author-email: victor.stinner@gmail.com
License: BSD (2-clause)
Platform: UNKNOWN
Classifier: Development Status :: 5 - Production/Stable
Classifier: Intended Audience :: Developers
Classifier: License :: OSI Approved :: BSD License
Classifier: Operating System :: OS Independent
Classifier: Natural Language :: English
Classifier: Programming Language :: C
Classifier: Programming Language :: Python
Classifier: Programming Language :: Python :: 3
Classifier: Topic :: Software Development :: Debuggers
Classifier: Topic :: Software Development :: Libraries :: Python Modules
